ibwebapi/__init__.py
ibkr_api-0.0.0.1.dist-info/METADATA
ibkr_api-0.0.0.1.dist-info/WHEEL
ibkr_api-0.0.0.1.dist-info/top_level.txt
ibkr_api-0.0.0.1.dist-info/RECORD
