Metadata-Version: 2.1
Name: ibkr-api
Version: 0.0.0.1
Summary: Asynchronous framework for IBKR's new web API.
Home-page: UNKNOWN
Author: louisnw
License: MIT
Platform: UNKNOWN
Requires-Python: >=3.8
